miniupnpc.cpython-310-darwin.so
miniupnpc-2.3.3.dist-info/RECORD
miniupnpc-2.3.3.dist-info/WHEEL
miniupnpc-2.3.3.dist-info/top_level.txt
miniupnpc-2.3.3.dist-info/METADATA
miniupnpc-2.3.3.dist-info/licenses/LICENSE
