Metadata-Version: 2.1
Name: miniupnpc
Version: 2.3.3
Summary: MiniUPnP IGD client
Home-page: https://miniupnp.tuxfamily.org/
Author: Thomas BERNARD
Author-email: miniupnp@free.fr
License: BSD 3-Clause License
License-File: LICENSE
